waitforoutput/__init__.py
waitforoutput/__main__.py
waitforoutput/app.py
waitforoutput/testing.py
waitforoutput-1.0.1.dist-info/AUTHORS
waitforoutput-1.0.1.dist-info/LICENSE
waitforoutput-1.0.1.dist-info/METADATA
waitforoutput-1.0.1.dist-info/WHEEL
waitforoutput-1.0.1.dist-info/entry_points.txt
waitforoutput-1.0.1.dist-info/pbr.json
waitforoutput-1.0.1.dist-info/top_level.txt
waitforoutput-1.0.1.dist-info/RECORD
