Metadata-Version: 2.1
Name: waitforoutput
Version: 1.0.1
Summary: Waits for a pattern to match output of a command or docker container logs.
Home-page: https://riotkit.org
Author: RiotKit non-profit organization
Author-email: riotkit@riseup.net
License: Apache-2
Keywords: setup,distutils
Platform: UNKNOWN
Classifier: Development Status :: 5 - Production/Stable
Classifier: Environment :: Console
Classifier: Intended Audience :: Developers
Classifier: Intended Audience :: System Administrators
Classifier: Intended Audience :: Information Technology
Classifier: License :: OSI Approved :: Apache Software License
Classifier: Operating System :: POSIX
Classifier: Programming Language :: Python :: 3 :: Only
Requires-Dist: rkd (>=2.3.5.dev24)
Requires-Dist: rkd-python (>=2.3.5.dev24)
